Organization/ChenTienFu/dlab/multimodule/mux.v
module mux (
    input       reset_n,
    input       clk_i,
    input       sel,
	input [7:0] input1,
	input [7:0] input2,
    output reg [7:0] result
);

always @( posedge clk_i ) begin
    if( !reset_n ) begin
        result <= 0;
    end
    else begin
        case( sel )  
            1'b0:
				result <= input1;
            1'b1:
				result <= input2;
            default:
				result <= result;
		endcase  
    end
end

endmodule

Organization/ChenTienFu/dlab/multimodule/multiplier.v
module multiplier(
    input        reset_n,
    input        clk_i,
	input      [3:0] input1,
	input      [3:0] input2,
	output reg [7:0] multiplied
);

always @( posedge clk_i ) begin
	if( !reset_n ) begin
		multiplied <= 0;
	end
	else begin
		multiplied <= input1 * input2;
	end
end

endmodule

Organization/ChenTienFu/dlab/multimodule/adder.v
module adder(
    input      reset_n,
    input      clk_i,
	input      [3:0] input1,
	input      [3:0] input2,
	output reg [7:0] added
);

always @( posedge clk_i ) begin
	if( !reset_n ) begin
		added <= 0;
	end
	else begin
		added <= input1 + input2;
	end
end
endmodule

Organization/ChenTienFu/dlab/multimodule/add_or_multiply.v
module add_or_multiply(
    input        reset_n,
    input        clk_i,
	input        sel,
	input  [3:0] input1,
	input  [3:0] input2,
	output [7:0] selected
);

wire [7:0] added;
wire [7:0] multiplied;

adder add(
    .reset_n(reset_n),
    .clk_i(clk_i),
	.input1(input1),
	.input2(input2),
	.added(added)
);

multiplier multiply(
    .reset_n(reset_n),
    .clk_i(clk_i),
	.input1(input1),
	.input2(input2),
	.multiplied(multiplied)
);

mux mux(
    .reset_n(reset_n),
    .clk_i(clk_i),
    .sel(sel),
	.input1(added),
	.input2(multiplied),
    .result(selected)
);

endmodule

Organization/陳添福/dlab/multimodule/testbench.v
`timescale 1ns/1ps

module testbench();

reg         reset_n;
reg         clk_n;
reg         sel;
reg   [3:0] input1;
reg   [3:0] input2;

wire  [7:0] selected;

add_or_multiply demo(
    .reset_n(reset_n),
    .clk_i(clk_n),
	.sel(sel),
	.input1(input1),
	.input2(input2),
	.selected(selected)
);

parameter           CYCLE = 10;
always #(CYCLE/2.0) clk_n = ~clk_n;

initial begin

clk_n = 1;
reset_n = 1;
input1 = 4'd5;
input2 = 4'd3;

$dumpfile("testbench.vcd");
$dumpvars( 0, demo );

# 10
reset_n = 0;

# 10
reset_n = 1;
sel = 2'b00;

# 20
sel = 2'b01;

# 15
input1 = 4'd4;
input2 = 4'd7;

# 20
sel = 2'b00;

# 20
sel = 2'b01;

# 20

$finish;
end
endmodule

Organization/陳添福/dlab/multimodule/testbench.vcd
$date
	Wed Mar 11 18:31:55 2020
$end
$version
	Icarus Verilog
$end
$timescale
	1ps
$end
$scope module testbench $end
$scope module demo $end
$var wire 1 ! clk_i $end
$var wire 4 " input1 [3:0] $end
$var wire 4 # input2 [3:0] $end
$var wire 1 $ reset_n $end
$var wire 1 % sel $end
$var wire 8 & selected [7:0] $end
$var wire 8 ' multiplied [7:0] $end
$var wire 8 ( added [7:0] $end
$scope module add $end
$var wire 1 ! clk_i $end
$var wire 4 ) input1 [3:0] $end
$var wire 4 * input2 [3:0] $end
$var wire 1 $ reset_n $end
$var reg 8 + added [7:0] $end
$upscope $end
$scope module multiply $end
$var wire 1 ! clk_i $end
$var wire 4 , input1 [3:0] $end
$var wire 4 - input2 [3:0] $end
$var wire 1 $ reset_n $end
$var reg 8 . multiplied [7:0] $end
$upscope $end
$scope module mux $end
$var wire 1 ! clk_i $end
$var wire 8 / input1 [7:0] $end
$var wire 8 0 input2 [7:0] $end
$var wire 1 $ reset_n $end
$var wire 1 % sel $end
$var reg 8 1 result [7:0] $end
$upscope $end
$upscope $end
$upscope $end
$enddefinitions $end
#0
$dumpvars
bx 1
b1111 0
b1000 /
b1111 .
b11 -
b101 ,
b1000 +
b11 *
b101 )
b1000 (
b1111 '
bx &
x%
1$
b11 #
b101 "
1!
$end
#5000
0!
#10000
b0 &
b0 1
b0 '
b0 .
b0 0
b0 (
b0 +
b0 /
1!
0$
#15000
0!
#20000
b1000 (
b1000 +
b1000 /
b1111 '
b1111 .
b1111 0
1!
0%
1$
#25000
0!
#30000
b1000 &
b1000 1
1!
#35000
0!
#40000
b1111 &
b1111 1
1!
1%
#45000
0!
#50000
1!
#55000
0!
b111 #
b111 *
b111 -
b100 "
b100 )
b100 ,
#60000
b1011 (
b1011 +
b1011 /
b11100 '
b11100 .
b11100 0
1!
#65000
0!
#70000
b11100 &
b11100 1
1!
#75000
0!
0%
#80000
b1011 &
b1011 1
1!
#85000
0!
#90000
1!
#95000
0!
1%
#100000
b11100 &
b11100 1
1!
